<?xml version="1.0" encoding="UTF-8"?>
<objects serializationModel="Studio.01.09.00">
    <object class="AudioFile" id="{baaa5d63-ae15-469e-8720-8a2491881f5e}">
        <property name="assetPath">
            <value>Powers/Repulse/End1.wav</value>
        </property>
        <property name="frequencyInKHz">
            <value>44.0999985</value>
        </property>
        <property name="channelCount">
            <value>2</value>
        </property>
        <property name="length">
            <value>0.66634920634920636</value>
        </property>
        <relationship name="masterAssetFolder">
            <destination>{0c26c50b-3b4d-4f17-81a2-c5cf4030f8d0}</destination>
        </relationship>
    </object>
</objects>
